{
  "kind": "collectionType",
  "collectionName": "contracts",
  "info": {
    "singularName": "contract",
    "pluralName": "contracts",
    "displayName": "contract",
    "description": ""
  },
  "options": {
    "draftAndPublish": false
  },
  "pluginOptions": {},
  "attributes": {
    "address": {
      "type": "text",
      "required": true,
      "unique": true
    },
    "reference": {
      "type": "text",
      "required": true,
      "unique": true
    },
    "name": {
      "type": "string"
    },
    "isSwap": {
      "type": "boolean",
      "default": false,
      "required": true
    },
    "code": {
      "type": "richtext"
    },
    "version": {
      "type": "string"
    },
    "chain": {
      "type": "string"
    },
    "path": {
      "type": "string"
    },
    "fullname": {
      "type": "text"
    },
    "functions": {
      "type": "richtext"
    },
    "events": {
      "type": "richtext"
    },
    "codeClean": {
      "type": "richtext"
    },
    "author": {
      "type": "string"
    },
    "title": {
      "type": "string"
    },
    "flagSwap": {
      "type": "boolean",
      "default": false
    },
    "flagWithdraw": {
      "type": "boolean",
      "default": false
    }
  }
}
